monoalpha/__init__.py
monoalpha/commandline.py
monoalpha/main.py
monoalpha-1.0.4.dist-info/LICENSE
monoalpha-1.0.4.dist-info/METADATA
monoalpha-1.0.4.dist-info/WHEEL
monoalpha-1.0.4.dist-info/entry_points.txt
monoalpha-1.0.4.dist-info/top_level.txt
monoalpha-1.0.4.dist-info/RECORD
