Metadata-Version: 2.1
Name: monoalpha
Version: 1.0.4
Summary: A simple monoalphabetic cipher program.
Home-page: UNKNOWN
Author: Toby Govin-Fowler
Author-email: tobygovinfowler@gmail.com
License: MIT
Keywords: cipher monoalphabetic encrypt
Platform: UNKNOWN
Classifier: Development Status :: 5 - Production/Stable
Classifier: Intended Audience :: Developers
Classifier: Topic :: Security :: Cryptography
Classifier: License :: OSI Approved :: MIT License
Classifier: Programming Language :: Python
Classifier: Programming Language :: Python :: 2
Classifier: Programming Language :: Python :: 3
